{
    "characterName": "Ashelem",
    "characterInfo": {
        "Ethnicity": "Alethi",
        "Nationality": "Alethi",
        "Gender": "Male",
        "Status": "Unknown",
        "Occupation": "Soldier",
        "Appears in": "The Way of Kings"
    },
    "characterImage": null,
    "characterDescription": "Ashelem was a soldier in Dalinar's army on the Shattered Plains who reported to Havarah - Dalinar's bridgelord - that the archery company was ready for an upcoming battle with the Parshendi.\r\n",
    "characterDetails": {
        "Biography": "",
        "Appearance": "",
        "Personality": "",
        "History": "",
        "Beliefs": "",
        "Characteristics": "",
        "Character": "",
        "Abilities": "",
        "Relationships": "",
        "Speculation": "",
        "Notes": "",
        "Trivia": ""
    }
}