{
    "characterName": "Auxiliary",
    "characterInfo": {
        "Race": "Spren",
        "Ethnicity": "Unknown",
        "Nationality": "Shadesmar",
        "Gender": "Unknown",
        "Status": "Dead",
        "Abilities": "Nahel bonding, affording Surgebinding",
        "Title(s)": "Highspren",
        "Appears in": "The Sunlit Man"
    },
    "characterImage": null,
    "characterDescription": "Auxiliary is a dead highspren that is bonded to Nomad.\r\n",
    "characterDetails": {
        "Biography": "",
        "Appearance": "",
        "Personality": "",
        "History": "",
        "Beliefs": "",
        "Characteristics": "",
        "Character": "",
        "Abilities": "",
        "Relationships": "",
        "Speculation": "",
        "Notes": "",
        "Trivia": ""
    }
}