{
    "characterName": "Durk",
    "characterInfo": {
        "Ethnicity": "Unknown",
        "Nationality": "Unknown",
        "Gender": "Male",
        "Status": "Unknown",
        "Appears in": "The Way of Kings (mentioned)"
    },
    "characterImage": null,
    "characterDescription": "Durk is an influence from Kaladin's past. He was a man who cared only for his own skin.\r\nStill, it remains unknown just when Durk and Kaladin met. However, at some point before Kaladin was enslaved, Durk told Kaladin that he was a natural born soldier and an artist with the spear.",
    "characterDetails": {
        "Biography": "",
        "Appearance": "",
        "Personality": "",
        "History": "",
        "Beliefs": "",
        "Characteristics": "",
        "Character": "Durk is a fairly superstitious man; he wears a pair of 'lucky boots' into every battle.",
        "Abilities": "",
        "Relationships": "",
        "Speculation": "",
        "Notes": "",
        "Trivia": ""
    }
}