{
    "characterName": "Jenin",
    "characterInfo": {
        "Ethnicity": "Alethi",
        "Nationality": "Alethi",
        "Gender": "Male",
        "Status": "Unknown",
        "Occupation": "Soldier",
        "Appears in": "Oathbringer"
    },
    "characterImage": null,
    "characterDescription": "Jenin is a soldier among Dalinar's elites of thirty-four years ago. He wields a short bow and, unhooking it from his back, shoots the horse upon which Yezriar is riding.",
    "characterDetails": {
        "Biography": "",
        "Appearance": "",
        "Personality": "",
        "History": "",
        "Beliefs": "",
        "Characteristics": "",
        "Character": "",
        "Abilities": "",
        "Relationships": "",
        "Speculation": "",
        "Notes": "",
        "Trivia": ""
    }
}